admirepred/blast_db/10e-2.txt
admirepred/blast_db/10e-2_results.txt
admirepred/blast_db/exosomal_db.ndb
admirepred/blast_db/exosomal_db.nhr
admirepred/blast_db/exosomal_db.nin
admirepred/blast_db/exosomal_db.nog
admirepred/blast_db/exosomal_db.nos
admirepred/blast_db/exosomal_db.not
admirepred/blast_db/exosomal_db.nsq
admirepred/blast_db/exosomal_db.ntf
admirepred/blast_db/exosomal_db.nto
admirepred/blast_db/exosomal_seq.fa
admirepred/data/feature_names_tfidf.csv
admirepred/model/admirepred_et_model.pkl
admirepred/output/example_classification_ML.csv
admirepred/output/example_classification_hybrid.csv
admirepred/python_scripts/__init__.py
admirepred/python_scripts/admirepred.py
admirepred-1.0.0.dist-info/LICENSE.txt
admirepred-1.0.0.dist-info/METADATA
admirepred-1.0.0.dist-info/WHEEL
admirepred-1.0.0.dist-info/entry_points.txt
admirepred-1.0.0.dist-info/top_level.txt
admirepred-1.0.0.dist-info/RECORD
