Metadata-Version: 2.2
Name: admirepred
Version: 1.0.0
Summary: A tool to predict abundant miRNA in exosomes
Home-page: https://github.com/raghavagps/admirepred
Author: Akanksha
Author-email: akankshaar@iiitd.ac.in
License: MIT
Requires-Python: >=3.9
License-File: LICENSE.txt
Requires-Dist: numpy
Requires-Dist: pandas
Requires-Dist: scikit-learn==1.6.1
Requires-Dist: joblib
Requires-Dist: argparse
Provides-Extra: dev
Requires-Dist: pytest>=7.0; extra == "dev"
Requires-Dist: twine>=4.0.2; extra == "dev"
Dynamic: description
Dynamic: description-content-type
Dynamic: home-page
Dynamic: provides-extra
Dynamic: requires-dist
Dynamic: requires-python
Dynamic: summary
